n0translate/__init__.py
n0translate/create_m3u.py
n0translate/n0translit.py
n0translate/test/__init__.py
n0translate/test/__main__.py
n0translate/test/test_n0translate.py
n0translate-0.2.0.dist-info/LICENSE
n0translate-0.2.0.dist-info/METADATA
n0translate-0.2.0.dist-info/WHEEL
n0translate-0.2.0.dist-info/top_level.txt
n0translate-0.2.0.dist-info/RECORD
